hmm_stock_forecast/__init__.py
hmm_stock_forecast/data/__init__.py
hmm_stock_forecast/data/data.py
hmm_stock_forecast/error/__init__.py
hmm_stock_forecast/error/error.py
hmm_stock_forecast/forecast.py
hmm_stock_forecast/hmm/__init__.py
hmm_stock_forecast/hmm/criteria.py
hmm_stock_forecast/hmm/hmm.py
hmm_stock_forecast/hmm/ihmm.py
hmm_stock_forecast/hmm/utils.py
hmm_stock_forecast/main.py
hmm_stock_forecast/plot/__init__.py
hmm_stock_forecast/plot/plot.py
hmm_stock_forecast/utils/__init__.py
hmm_stock_forecast/utils/args.py
hmm_stock_forecast/utils/logging.py
hmm_stock_forecast-1.0.dist-info/entry_points.txt
hmm_stock_forecast-1.0.dist-info/LICENSE
hmm_stock_forecast-1.0.dist-info/WHEEL
hmm_stock_forecast-1.0.dist-info/METADATA
hmm_stock_forecast-1.0.dist-info/RECORD
