Metadata-Version: 2.1
Name: hmm-stock-forecast
Version: 1.0
Summary: Stock forecasting based on (gaussian) Hidden Markov Model
License: MIT
Author: Martin Forejt
Requires-Python: >=3.8,<4.0
Classifier: License :: OSI Approved :: MIT License
Classifier: Programming Language :: Python :: 3
Classifier: Programming Language :: Python :: 3.10
Classifier: Programming Language :: Python :: 3.8
Classifier: Programming Language :: Python :: 3.9
Requires-Dist: argparse (>=1.4.0,<2.0.0)
Requires-Dist: matplotlib (>=3.5.1,<4.0.0)
Requires-Dist: numpy (>=1.22.1,<2.0.0)
Requires-Dist: pandas (>=1.3.5,<2.0.0)
Requires-Dist: pandas-datareader (>=0.10.0,<0.11.0)
Requires-Dist: pomegranate (>=0.14.7,<0.15.0)
Requires-Dist: recordclass (>=0.17.1,<0.18.0)
Requires-Dist: sklearn (>=0.0,<0.1)
Requires-Dist: tqdm (>=4.62.3,<5.0.0)
